{
  "slug": "gabarda-de-anza-trail",
  "lat": 35.48386516704092,
  "lon": -120.6450564406524,
  "flowLow": 100,
  "flowHigh": 900,
  "tresspass": false,
  "gauge": "paso",
  "ada": true,
  "directions": {
    "type": "FeatureCollection",
    "features": [
      {
        "type": "Feature",
        "geometry": {
          "type": "MultiLineString",
          "coordinates": [
            [
              [
                -120.6406,
                35.48914,
                0
              ],
              [
                -120.64058,
                35.4891,
                0
              ],
              [
                -120.64054,
                35.48907,
                0
              ],
              [
                -120.6405,
                35.48904,
                0
              ],
              [
                -120.64047,
                35.48902,
                0
              ],
              [
                -120.64043,
                35.48897,
                0
              ],
              [
                -120.64038,
                35.4889,
                0
              ],
              [
                -120.64037,
                35.48882,
                0
              ],
              [
                -120.64036,
                35.48872,
                0
              ],
              [
                -120.64034,
                35.48863,
                0
              ],
              [
                -120.64036,
                35.48855,
                0
              ],
              [
                -120.6404,
                35.48847,
                0
              ],
              [
                -120.64042,
                35.48839,
                0
              ],
              [
                -120.64042,
                35.48831,
                0
              ],
              [
                -120.64041,
                35.48822,
                0
              ],
              [
                -120.64038,
                35.48813,
                0
              ],
              [
                -120.64036,
                35.48805,
                0
              ],
              [
                -120.64034,
                35.48797,
                0
              ],
              [
                -120.64031,
                35.48788,
                0
              ],
              [
                -120.64027,
                35.48781,
                0
              ],
              [
                -120.64023,
                35.48773,
                0
              ],
              [
                -120.64018,
                35.48765,
                0
              ],
              [
                -120.64015,
                35.48757,
                0
              ],
              [
                -120.64013,
                35.48749,
                0
              ],
              [
                -120.64011,
                35.4874,
                0
              ],
              [
                -120.64009,
                35.48732,
                0
              ],
              [
                -120.64007,
                35.48724,
                0
              ],
              [
                -120.64007,
                35.48715,
                0
              ],
              [
                -120.64007,
                35.48707,
                0
              ],
              [
                -120.64007,
                35.48699,
                0
              ],
              [
                -120.64006,
                35.48687,
                0
              ],
              [
                -120.64013,
                35.48682,
                0
              ],
              [
                -120.64037,
                35.48665,
                0
              ],
              [
                -120.64046,
                35.48659,
                0
              ],
              [
                -120.64054,
                35.48654,
                0
              ],
              [
                -120.64061,
                35.48649,
                0
              ],
              [
                -120.64067,
                35.48644,
                0
              ],
              [
                -120.64073,
                35.48638,
                0
              ],
              [
                -120.64077,
                35.48631,
                0
              ],
              [
                -120.64077,
                35.48623,
                0
              ],
              [
                -120.64067,
                35.48619,
                0
              ],
              [
                -120.6406,
                35.48613,
                0
              ],
              [
                -120.64055,
                35.48607,
                0
              ],
              [
                -120.64049,
                35.48601,
                0
              ],
              [
                -120.64043,
                35.48594,
                0
              ],
              [
                -120.64036,
                35.48588,
                0
              ],
              [
                -120.64026,
                35.48591,
                0
              ],
              [
                -120.64017,
                35.48595,
                0
              ],
              [
                -120.64007,
                35.48594,
                0
              ],
              [
                -120.63999,
                35.48592,
                0
              ],
              [
                -120.6399,
                35.48588,
                0
              ],
              [
                -120.63983,
                35.48581,
                0
              ],
              [
                -120.63978,
                35.48574,
                0
              ],
              [
                -120.63973,
                35.48566,
                0
              ],
              [
                -120.63969,
                35.48558,
                0
              ],
              [
                -120.63967,
                35.48549,
                0
              ],
              [
                -120.63964,
                35.4854,
                0
              ],
              [
                -120.63962,
                35.4853,
                0
              ],
              [
                -120.6397,
                35.48525,
                0
              ],
              [
                -120.63983,
                35.48522,
                0
              ],
              [
                -120.63994,
                35.48519,
                0
              ],
              [
                -120.64003,
                35.48514,
                0
              ],
              [
                -120.64011,
                35.48509,
                0
              ],
              [
                -120.64019,
                35.48504,
                0
              ],
              [
                -120.64028,
                35.48499,
                0
              ],
              [
                -120.64036,
                35.48494,
                0
              ],
              [
                -120.64044,
                35.48489,
                0
              ],
              [
                -120.64052,
                35.48485,
                0
              ],
              [
                -120.6406,
                35.4848,
                0
              ],
              [
                -120.6407,
                35.48476,
                0
              ],
              [
                -120.64079,
                35.48472,
                0
              ],
              [
                -120.64088,
                35.48469,
                0
              ],
              [
                -120.64097,
                35.48465,
                0
              ],
              [
                -120.64106,
                35.48462,
                0
              ],
              [
                -120.64115,
                35.48458,
                0
              ],
              [
                -120.64123,
                35.48452,
                0
              ],
              [
                -120.64131,
                35.48446,
                0
              ],
              [
                -120.64139,
                35.4844,
                0
              ],
              [
                -120.64147,
                35.48434,
                0
              ],
              [
                -120.64155,
                35.48427,
                0
              ],
              [
                -120.64163,
                35.48421,
                0
              ],
              [
                -120.64172,
                35.48416,
                0
              ],
              [
                -120.64181,
                35.48411,
                0
              ],
              [
                -120.64189,
                35.48416,
                0
              ],
              [
                -120.64195,
                35.48422,
                0
              ],
              [
                -120.64204,
                35.48425,
                0
              ],
              [
                -120.64213,
                35.48426,
                0
              ],
              [
                -120.64223,
                35.48424,
                0
              ],
              [
                -120.64232,
                35.48422,
                0
              ],
              [
                -120.64243,
                35.4842,
                0
              ],
              [
                -120.64253,
                35.4842,
                0
              ],
              [
                -120.64263,
                35.48423,
                0
              ],
              [
                -120.64272,
                35.48427,
                0
              ],
              [
                -120.64282,
                35.48429,
                0
              ],
              [
                -120.64291,
                35.48431,
                0
              ],
              [
                -120.64301,
                35.48433,
                0
              ],
              [
                -120.6431,
                35.48433,
                0
              ],
              [
                -120.64319,
                35.48433,
                0
              ],
              [
                -120.64329,
                35.48432,
                0
              ],
              [
                -120.64339,
                35.48431,
                0
              ],
              [
                -120.64348,
                35.48429,
                0
              ],
              [
                -120.64357,
                35.48427,
                0
              ],
              [
                -120.64367,
                35.48426,
                0
              ],
              [
                -120.64376,
                35.48424,
                0
              ],
              [
                -120.64384,
                35.48419,
                0
              ],
              [
                -120.64388,
                35.4841,
                0
              ],
              [
                -120.64395,
                35.48404,
                0
              ],
              [
                -120.64402,
                35.48401,
                0
              ],
              [
                -120.64412,
                35.48397,
                0
              ],
              [
                -120.64421,
                35.48394,
                0
              ],
              [
                -120.64429,
                35.4839,
                0
              ],
              [
                -120.64438,
                35.48385,
                0
              ],
              [
                -120.64447,
                35.48378,
                0
              ],
              [
                -120.64454,
                35.4837,
                0
              ],
              [
                -120.64461,
                35.48363,
                0
              ],
              [
                -120.64466,
                35.48354,
                0
              ],
              [
                -120.64454,
                35.4835,
                0
              ],
              [
                -120.64458,
                35.48341,
                0
              ],
              [
                -120.64466,
                35.48336,
                0
              ],
              [
                -120.64466,
                35.48326,
                0
              ],
              [
                -120.64468,
                35.48339,
                0
              ],
              [
                -120.64469,
                35.48348,
                0
              ],
              [
                -120.64473,
                35.48357,
                0
              ],
              [
                -120.64478,
                35.48364,
                0
              ],
              [
                -120.64499,
                35.48369,
                0
              ]
            ]
          ],
          "bbox": [
            -120.63962,
            35.48914,
            -120.64499,
            35.48326
          ]
        }
      }
    ]
  },
  "translate": {
    "en": {
      "title": "Gabarda de Anza Trail",
      "tags": "accessPoint",
      "directions": "Park alongside the road and look for the trailhead near the entrance of the water treatment plant.",
      "body": "A scenic trail that leads to a beautiful spot along the river. The trail is well-maintained and offers great views."
    },
    "es": {
      "title": "Sendero Gabarda de Anza",
      "tags": "accessPoint",
      "directions": "Estacione al lado de la carretera y busque el inicio del sendero cerca de la entrada de la planta de tratamiento de agua.",
      "body": "Un sendero pintoresco que conduce a un hermoso lugar a orillas del río. El sendero está bien mantenido y ofrece magníficas vistas."
    }
  },
  "photos": [
    {
      "filename": "IMG_9750.jpg",
      "originalFilename": "IMG_9750.HEIC",
      "date": "2026-03-14",
      "lat": 35.483455373389944,
      "lon": -120.64469335498377,
      "cfs": 78.8,
      "height": null
    },
    {
      "filename": "IMG_9751.jpg",
      "originalFilename": "IMG_9751.HEIC",
      "date": "2026-03-14",
      "lat": 35.483455373389944,
      "lon": -120.64469335498377,
      "cfs": 78.8,
      "height": null
    },
    {
      "filename": "IMG_9752.jpg",
      "originalFilename": "IMG_9752.HEIC",
      "date": "2026-03-14",
      "lat": 35.483455373389944,
      "lon": -120.64469335498377,
      "cfs": 78.8,
      "height": null
    },
    {
      "filename": "IMG_9753.webm",
      "originalFilename": "IMG_9753.MOV",
      "date": "2026-03-14",
      "lat": 35.48400053704755,
      "lon": -120.64423479613241,
      "cfs": 78.8,
      "height": null,
      "type": "video"
    }
  ],
  "mileage": 0.74,
  "county": "San Luis Obispo"
}
